ethToSql/EtherScamHTMLParser.py
ethToSql/SeqlDB.py
ethToSql/__init__.py
ethToSql/ethToSqlMain.py
ethToSql-0.4.dist-info/METADATA
ethToSql-0.4.dist-info/RECORD
ethToSql-0.4.dist-info/WHEEL
ethToSql-0.4.dist-info/top_level.txt
