Metadata-Version: 2.1
Name: ethToSql
Version: 0.4
Summary: Read Data from an Ethereum node and insert into a SQL database
Home-page: https://github.com/dmenin/EthToSql
Author: Diego
Author-email: dmenin@gmail.com
License: MIT
Platform: UNKNOWN
Classifier: Programming Language :: Python :: 3
Classifier: License :: OSI Approved :: MIT License
Classifier: Operating System :: OS Independent
Requires-Dist: tqdm
